[{"objectID": 311699, "id": 311699, "consumer": {"id": 244435, "hasAvatar": true, "site": "/api/site_configs/309", "publicName": "Irina S.", "avatar": "8f2ffac5cf5053d69ae589454113a738.png"}, "status": 1, "dateValidityStart": 1740160217, "dateValidityEnd": 1740290400, "tickets": [{"id": 311699, "product": {"id": 14614, "name": {"en": "WEEKEND REGULAR", "nl": "WEEKEND REGULAR", "de": "", "es": "", "fr": "", "pt": "", "no": ""}, "description": {"en": "Late Phase", "nl": "Late Phase", "de": "", "es": "", "fr": "", "pt": "", "no": ""}, "partner": "/api/partners/1", "category": {"id": 4054, "name": {"en": "WEEKEND TICKETS", "de": "WEEKEND TICKETS", "nl": "WEEKEND TICKETS", "fr": "WEEKEND TICKETS"}, "endDate": 1740286800, "venue": "/api/venues/161", "image": "5487e79fa0ccd0b79e5d4a4c8ced005d.jpg", "contentUrl": null, "imageUrl": "5487e79fa0ccd0b79e5d4a4c8ced005d.jpg", "imageName": "5487e79fa0ccd0b79e5d4a4c8ced005d.jpg?t=1738857844"}, "saleStart": 1724148000, "saleEnd": 1740279600, "createdAt": 1738857695, "updatedAt": 1738857695, "isActive": true}, "resaleValue": 12150, "facialValue": 13500, "consumer": {"id": 244435, "hasAvatar": true, "site": "/api/site_configs/309", "publicName": "Irina S.", "avatar": "8f2ffac5cf5053d69ae589454113a738.png"}, "status": 1, "currency": "EUR", "usageDateStart": 1739790000, "usageDateEnd": 1740290400, "purchaseFees": 1458, "seats": [], "notice": null, "fixedFee": 0}], "nbCartTickets": 0, "dynamicStatus": 1, "minPrice": 13608, "nbAvailableTickets": 1, "severability": false}, {"objectID": 307974, "id": 307974, "consumer": {"id": 242601, "hasAvatar": true, "site": "/api/site_configs/309", "publicName": "Liam T.", "avatar": "b8f93fb07624a1d860c2edfdf330c59b.png"}, "status": 1, "dateValidityStart": 1739812473, "dateValidityEnd": 1740290400, "tickets": [{"id": 307974, "product": {"id": 14614, "name": {"en": "WEEKEND REGULAR", "nl": "WEEKEND REGULAR", "de": "", "es": "", "fr": "", "pt": "", "no": ""}, "description": {"en": "Late Phase", "nl": "Late Phase", "de": "", "es": "", "fr": "", "pt": "", "no": ""}, "partner": "/api/partners/1", "category": {"id": 4054, "name": {"en": "WEEKEND TICKETS", "de": "WEEKEND TICKETS", "nl": "WEEKEND TICKETS", "fr": "WEEKEND TICKETS"}, "endDate": 1740286800, "venue": "/api/venues/161", "image": "5487e79fa0ccd0b79e5d4a4c8ced005d.jpg", "contentUrl": null, "imageUrl": "5487e79fa0ccd0b79e5d4a4c8ced005d.jpg", "imageName": "5487e79fa0ccd0b79e5d4a4c8ced005d.jpg?t=1738857844"}, "saleStart": 1724148000, "saleEnd": 1740279600, "createdAt": 1738857695, "updatedAt": 1738857695, "isActive": true}, "resaleValue": 12150, "facialValue": 13500, "consumer": {"id": 242601, "hasAvatar": true, "site": "/api/site_configs/309", "publicName": "Liam T.", "avatar": "b8f93fb07624a1d860c2edfdf330c59b.png"}, "status": 1, "currency": "EUR", "usageDateStart": 1739790000, "usageDateEnd": 1740290400, "purchaseFees": 1458, "seats": [], "notice": null, "fixedFee": 0}], "nbCartTickets": 0, "dynamicStatus": 1, "minPrice": 13608, "nbAvailableTickets": 1, "severability": false}, {"objectID": 309622, "id": 309622, "consumer": {"id": 242709, "hasAvatar": true, "site": "/api/site_configs/309", "publicName": "Matan L.", "avatar": "e46524d2c08526b4a5d7536d20a57e28.png"}, "status": 1, "dateValidityStart": 1740037243, "dateValidityEnd": 1740290400, "tickets": [{"id": 309622, "product": {"id": 14614, "name": {"en": "WEEKEND REGULAR", "nl": "WEEKEND REGULAR", "de": "", "es": "", "fr": "", "pt": "", "no": ""}, "description": {"en": "Late Phase", "nl": "Late Phase", "de": "", "es": "", "fr": "", "pt": "", "no": ""}, "partner": "/api/partners/1", "category": {"id": 4054, "name": {"en": "WEEKEND TICKETS", "de": "WEEKEND TICKETS", "nl": "WEEKEND TICKETS", "fr": "WEEKEND TICKETS"}, "endDate": 1740286800, "venue": "/api/venues/161", "image": "5487e79fa0ccd0b79e5d4a4c8ced005d.jpg", "contentUrl": null, "imageUrl": "5487e79fa0ccd0b79e5d4a4c8ced005d.jpg", "imageName": "5487e79fa0ccd0b79e5d4a4c8ced005d.jpg?t=1738857844"}, "saleStart": 1724148000, "saleEnd": 1740279600, "createdAt": 1738857695, "updatedAt": 1738857695, "isActive": true}, "resaleValue": 12150, "facialValue": 13500, "consumer": {"id": 242709, "hasAvatar": true, "site": "/api/site_configs/309", "publicName": "Matan L.", "avatar": "e46524d2c08526b4a5d7536d20a57e28.png"}, "status": 1, "currency": "EUR", "usageDateStart": 1739790000, "usageDateEnd": 1740290400, "purchaseFees": 1458, "seats": [], "notice": null, "fixedFee": 0}], "nbCartTickets": 0, "dynamicStatus": 1, "minPrice": 13608, "nbAvailableTickets": 1, "severability": false}, {"objectID": 308224, "id": 308224, "consumer": {"id": 242741, "hasAvatar": true, "site": "/api/site_configs/309", "publicName": "Jamie S.", "avatar": "02c3fcfdf5639ea13b996ed742fd7736.png"}, "status": 1, "dateValidityStart": 1739832899, "dateValidityEnd": 1740290400, "tickets": [{"id": 308224, "product": {"id": 14614, "name": {"en": "WEEKEND REGULAR", "nl": "WEEKEND REGULAR", "de": "", "es": "", "fr": "", "pt": "", "no": ""}, "description": {"en": "Late Phase", "nl": "Late Phase", "de": "", "es": "", "fr": "", "pt": "", "no": ""}, "partner": "/api/partners/1", "category": {"id": 4054, "name": {"en": "WEEKEND TICKETS", "de": "WEEKEND TICKETS", "nl": "WEEKEND TICKETS", "fr": "WEEKEND TICKETS"}, "endDate": 1740286800, "venue": "/api/venues/161", "image": "5487e79fa0ccd0b79e5d4a4c8ced005d.jpg", "contentUrl": null, "imageUrl": "5487e79fa0ccd0b79e5d4a4c8ced005d.jpg", "imageName": "5487e79fa0ccd0b79e5d4a4c8ced005d.jpg?t=1738857844"}, "saleStart": 1724148000, "saleEnd": 1740279600, "createdAt": 1738857695, "updatedAt": 1738857695, "isActive": true}, "resaleValue": 12150, "facialValue": 13500, "consumer": {"id": 242741, "hasAvatar": true, "site": "/api/site_configs/309", "publicName": "Jamie S.", "avatar": "02c3fcfdf5639ea13b996ed742fd7736.png"}, "status": 1, "currency": "EUR", "usageDateStart": 1739790000, "usageDateEnd": 1740290400, "purchaseFees": 1458, "seats": [], "notice": null, "fixedFee": 0}], "nbCartTickets": 0, "dynamicStatus": 1, "minPrice": 13608, "nbAvailableTickets": 1, "severability": false}, {"objectID": 308225, "id": 308225, "consumer": {"id": 242741, "hasAvatar": true, "site": "/api/site_configs/309", "publicName": "Jamie S.", "avatar": "02c3fcfdf5639ea13b996ed742fd7736.png"}, "status": 1, "dateValidityStart": 1739832913, "dateValidityEnd": 1740290400, "tickets": [{"id": 308225, "product": {"id": 14614, "name": {"en": "WEEKEND REGULAR", "nl": "WEEKEND REGULAR", "de": "", "es": "", "fr": "", "pt": "", "no": ""}, "description": {"en": "Late Phase", "nl": "Late Phase", "de": "", "es": "", "fr": "", "pt": "", "no": ""}, "partner": "/api/partners/1", "category": {"id": 4054, "name": {"en": "WEEKEND TICKETS", "de": "WEEKEND TICKETS", "nl": "WEEKEND TICKETS", "fr": "WEEKEND TICKETS"}, "endDate": 1740286800, "venue": "/api/venues/161", "image": "5487e79fa0ccd0b79e5d4a4c8ced005d.jpg", "contentUrl": null, "imageUrl": "5487e79fa0ccd0b79e5d4a4c8ced005d.jpg", "imageName": "5487e79fa0ccd0b79e5d4a4c8ced005d.jpg?t=1738857844"}, "saleStart": 1724148000, "saleEnd": 1740279600, "createdAt": 1738857695, "updatedAt": 1738857695, "isActive": true}, "resaleValue": 12150, "facialValue": 13500, "consumer": {"id": 242741, "hasAvatar": true, "site": "/api/site_configs/309", "publicName": "Jamie S.", "avatar": "02c3fcfdf5639ea13b996ed742fd7736.png"}, "status": 1, "currency": "EUR", "usageDateStart": 1739790000, "usageDateEnd": 1740290400, "purchaseFees": 1458, "seats": [], "notice": null, "fixedFee": 0}], "nbCartTickets": 0, "dynamicStatus": 1, "minPrice": 13608, "nbAvailableTickets": 1, "severability": false}, {"objectID": 310525, "id": 310525, "consumer": {"id": 243872, "hasAvatar": true, "site": "/api/site_configs/309", "publicName": "Vera S.", "avatar": "bfb83598cb821500938bc07c123f4bd8.png"}, "status": 1, "dateValidityStart": 1740121829, "dateValidityEnd": 1740290400, "tickets": [{"id": 310525, "product": {"id": 14614, "name": {"en": "WEEKEND REGULAR", "nl": "WEEKEND REGULAR", "de": "", "es": "", "fr": "", "pt": "", "no": ""}, "description": {"en": "Late Phase", "nl": "Late Phase", "de": "", "es": "", "fr": "", "pt": "", "no": ""}, "partner": "/api/partners/1", "category": {"id": 4054, "name": {"en": "WEEKEND TICKETS", "de": "WEEKEND TICKETS", "nl": "WEEKEND TICKETS", "fr": "WEEKEND TICKETS"}, "endDate": 1740286800, "venue": "/api/venues/161", "image": "5487e79fa0ccd0b79e5d4a4c8ced005d.jpg", "contentUrl": null, "imageUrl": "5487e79fa0ccd0b79e5d4a4c8ced005d.jpg", "imageName": "5487e79fa0ccd0b79e5d4a4c8ced005d.jpg?t=1738857844"}, "saleStart": 1724148000, "saleEnd": 1740279600, "createdAt": 1738857695, "updatedAt": 1738857695, "isActive": true}, "resaleValue": 12150, "facialValue": 13500, "consumer": {"id": 243872, "hasAvatar": true, "site": "/api/site_configs/309", "publicName": "Vera S.", "avatar": "bfb83598cb821500938bc07c123f4bd8.png"}, "status": 1, "currency": "EUR", "usageDateStart": 1739790000, "usageDateEnd": 1740290400, "purchaseFees": 1458, "seats": [], "notice": null, "fixedFee": 0}], "nbCartTickets": 0, "dynamicStatus": 1, "minPrice": 13608, "nbAvailableTickets": 1, "severability": false}, {"objectID": 308241, "id": 308241, "consumer": {"id": 242752, "hasAvatar": true, "site": "/api/site_configs/309", "publicName": "Iris M.", "avatar": "4223c64624c05ac1a59e44dd400bd94c.png"}, "status": 1, "dateValidityStart": 1739835278, "dateValidityEnd": 1740290400, "tickets": [{"id": 308241, "product": {"id": 14614, "name": {"en": "WEEKEND REGULAR", "nl": "WEEKEND REGULAR", "de": "", "es": "", "fr": "", "pt": "", "no": ""}, "description": {"en": "Late Phase", "nl": "Late Phase", "de": "", "es": "", "fr": "", "pt": "", "no": ""}, "partner": "/api/partners/1", "category": {"id": 4054, "name": {"en": "WEEKEND TICKETS", "de": "WEEKEND TICKETS", "nl": "WEEKEND TICKETS", "fr": "WEEKEND TICKETS"}, "endDate": 1740286800, "venue": "/api/venues/161", "image": "5487e79fa0ccd0b79e5d4a4c8ced005d.jpg", "contentUrl": null, "imageUrl": "5487e79fa0ccd0b79e5d4a4c8ced005d.jpg", "imageName": "5487e79fa0ccd0b79e5d4a4c8ced005d.jpg?t=1738857844"}, "saleStart": 1724148000, "saleEnd": 1740279600, "createdAt": 1738857695, "updatedAt": 1738857695, "isActive": true}, "resaleValue": 12150, "facialValue": 13500, "consumer": {"id": 242752, "hasAvatar": true, "site": "/api/site_configs/309", "publicName": "Iris M.", "avatar": "4223c64624c05ac1a59e44dd400bd94c.png"}, "status": 1, "currency": "EUR", "usageDateStart": 1739790000, "usageDateEnd": 1740290400, "purchaseFees": 1458, "seats": [], "notice": null, "fixedFee": 0}], "nbCartTickets": 0, "dynamicStatus": 1, "minPrice": 13608, "nbAvailableTickets": 1, "severability": false}, {"objectID": 311652, "id": 311652, "consumer": {"id": 243821, "hasAvatar": true, "site": "/api/site_configs/309", "publicName": "Alexandros K.", "avatar": "c63142e7d4518771259d34fce27afdbe.png"}, "status": 1, "dateValidityStart": 1740157499, "dateValidityEnd": 1740290400, "tickets": [{"id": 311652, "product": {"id": 14614, "name": {"en": "WEEKEND REGULAR", "nl": "WEEKEND REGULAR", "de": "", "es": "", "fr": "", "pt": "", "no": ""}, "description": {"en": "Late Phase", "nl": "Late Phase", "de": "", "es": "", "fr": "", "pt": "", "no": ""}, "partner": "/api/partners/1", "category": {"id": 4054, "name": {"en": "WEEKEND TICKETS", "de": "WEEKEND TICKETS", "nl": "WEEKEND TICKETS", "fr": "WEEKEND TICKETS"}, "endDate": 1740286800, "venue": "/api/venues/161", "image": "5487e79fa0ccd0b79e5d4a4c8ced005d.jpg", "contentUrl": null, "imageUrl": "5487e79fa0ccd0b79e5d4a4c8ced005d.jpg", "imageName": "5487e79fa0ccd0b79e5d4a4c8ced005d.jpg?t=1738857844"}, "saleStart": 1724148000, "saleEnd": 1740279600, "createdAt": 1738857695, "updatedAt": 1738857695, "isActive": true}, "resaleValue": 12150, "facialValue": 13500, "consumer": {"id": 243821, "hasAvatar": true, "site": "/api/site_configs/309", "publicName": "Alexandros K.", "avatar": "c63142e7d4518771259d34fce27afdbe.png"}, "status": 1, "currency": "EUR", "usageDateStart": 1739790000, "usageDateEnd": 1740290400, "purchaseFees": 1458, "seats": [], "notice": null, "fixedFee": 0}], "nbCartTickets": 0, "dynamicStatus": 1, "minPrice": 13608, "nbAvailableTickets": 1, "severability": false}, {"objectID": 308267, "id": 308267, "consumer": {"id": 242623, "hasAvatar": true, "site": "/api/site_configs/309", "publicName": "David M.", "avatar": "4b506546b082e41f4904caab584d80eb.png"}, "status": 1, "dateValidityStart": 1739849839, "dateValidityEnd": 1740290400, "tickets": [{"id": 308267, "product": {"id": 14614, "name": {"en": "WEEKEND REGULAR", "nl": "WEEKEND REGULAR", "de": "", "es": "", "fr": "", "pt": "", "no": ""}, "description": {"en": "Late Phase", "nl": "Late Phase", "de": "", "es": "", "fr": "", "pt": "", "no": ""}, "partner": "/api/partners/1", "category": {"id": 4054, "name": {"en": "WEEKEND TICKETS", "de": "WEEKEND TICKETS", "nl": "WEEKEND TICKETS", "fr": "WEEKEND TICKETS"}, "endDate": 1740286800, "venue": "/api/venues/161", "image": "5487e79fa0ccd0b79e5d4a4c8ced005d.jpg", "contentUrl": null, "imageUrl": "5487e79fa0ccd0b79e5d4a4c8ced005d.jpg", "imageName": "5487e79fa0ccd0b79e5d4a4c8ced005d.jpg?t=1738857844"}, "saleStart": 1724148000, "saleEnd": 1740279600, "createdAt": 1738857695, "updatedAt": 1738857695, "isActive": true}, "resaleValue": 12150, "facialValue": 13500, "consumer": {"id": 242623, "hasAvatar": true, "site": "/api/site_configs/309", "publicName": "David M.", "avatar": "4b506546b082e41f4904caab584d80eb.png"}, "status": 1, "currency": "EUR", "usageDateStart": 1739790000, "usageDateEnd": 1740290400, "purchaseFees": 1458, "seats": [], "notice": null, "fixedFee": 0}], "nbCartTickets": 0, "dynamicStatus": 1, "minPrice": 13608, "nbAvailableTickets": 1, "severability": false}, {"objectID": 311066, "id": 311066, "consumer": {"id": 243578, "hasAvatar": true, "site": "/api/site_configs/309", "publicName": "Walter S.", "avatar": "7a6824e91b2b7c0ea4df0beeb9171a7b.png"}, "status": 1, "dateValidityStart": 1740134374, "dateValidityEnd": 1740290400, "tickets": [{"id": 311066, "product": {"id": 14614, "name": {"en": "WEEKEND REGULAR", "nl": "WEEKEND REGULAR", "de": "", "es": "", "fr": "", "pt": "", "no": ""}, "description": {"en": "Late Phase", "nl": "Late Phase", "de": "", "es": "", "fr": "", "pt": "", "no": ""}, "partner": "/api/partners/1", "category": {"id": 4054, "name": {"en": "WEEKEND TICKETS", "de": "WEEKEND TICKETS", "nl": "WEEKEND TICKETS", "fr": "WEEKEND TICKETS"}, "endDate": 1740286800, "venue": "/api/venues/161", "image": "5487e79fa0ccd0b79e5d4a4c8ced005d.jpg", "contentUrl": null, "imageUrl": "5487e79fa0ccd0b79e5d4a4c8ced005d.jpg", "imageName": "5487e79fa0ccd0b79e5d4a4c8ced005d.jpg?t=1738857844"}, "saleStart": 1724148000, "saleEnd": 1740279600, "createdAt": 1738857695, "updatedAt": 1738857695, "isActive": true}, "resaleValue": 12150, "facialValue": 13500, "consumer": {"id": 243578, "hasAvatar": true, "site": "/api/site_configs/309", "publicName": "Walter S.", "avatar": "7a6824e91b2b7c0ea4df0beeb9171a7b.png"}, "status": 1, "currency": "EUR", "usageDateStart": 1739790000, "usageDateEnd": 1740290400, "purchaseFees": 1458, "seats": [], "notice": null, "fixedFee": 0}], "nbCartTickets": 0, "dynamicStatus": 1, "minPrice": 13608, "nbAvailableTickets": 1, "severability": false}, {"objectID": 309996, "id": 309996, "consumer": {"id": 243714, "hasAvatar": true, "site": "/api/site_configs/309", "publicName": "Paul J.", "avatar": "da03ef8ae24b6a6095e0970aec88f689.png"}, "status": 1, "dateValidityStart": 1740076609, "dateValidityEnd": 1740290400, "tickets": [{"id": 309996, "product": {"id": 14614, "name": {"en": "WEEKEND REGULAR", "nl": "WEEKEND REGULAR", "de": "", "es": "", "fr": "", "pt": "", "no": ""}, "description": {"en": "Late Phase", "nl": "Late Phase", "de": "", "es": "", "fr": "", "pt": "", "no": ""}, "partner": "/api/partners/1", "category": {"id": 4054, "name": {"en": "WEEKEND TICKETS", "de": "WEEKEND TICKETS", "nl": "WEEKEND TICKETS", "fr": "WEEKEND TICKETS"}, "endDate": 1740286800, "venue": "/api/venues/161", "image": "5487e79fa0ccd0b79e5d4a4c8ced005d.jpg", "contentUrl": null, "imageUrl": "5487e79fa0ccd0b79e5d4a4c8ced005d.jpg", "imageName": "5487e79fa0ccd0b79e5d4a4c8ced005d.jpg?t=1738857844"}, "saleStart": 1724148000, "saleEnd": 1740279600, "createdAt": 1738857695, "updatedAt": 1738857695, "isActive": true}, "resaleValue": 12150, "facialValue": 13500, "consumer": {"id": 243714, "hasAvatar": true, "site": "/api/site_configs/309", "publicName": "Paul J.", "avatar": "da03ef8ae24b6a6095e0970aec88f689.png"}, "status": 1, "currency": "EUR", "usageDateStart": 1739790000, "usageDateEnd": 1740290400, "purchaseFees": 1458, "seats": [], "notice": null, "fixedFee": 0}], "nbCartTickets": 0, "dynamicStatus": 1, "minPrice": 13608, "nbAvailableTickets": 1, "severability": false}, {"objectID": 310361, "id": 310361, "consumer": {"id": 45049, "hasAvatar": true, "site": "/api/site_configs/26", "publicName": "Lennard D.", "avatar": "a6835971b07994243412ed59f9c5f310.png"}, "status": 1, "dateValidityStart": 1740118701, "dateValidityEnd": 1740290400, "tickets": [{"id": 310361, "product": {"id": 14614, "name": {"en": "WEEKEND REGULAR", "nl": "WEEKEND REGULAR", "de": "", "es": "", "fr": "", "pt": "", "no": ""}, "description": {"en": "Late Phase", "nl": "Late Phase", "de": "", "es": "", "fr": "", "pt": "", "no": ""}, "partner": "/api/partners/1", "category": {"id": 4054, "name": {"en": "WEEKEND TICKETS", "de": "WEEKEND TICKETS", "nl": "WEEKEND TICKETS", "fr": "WEEKEND TICKETS"}, "endDate": 1740286800, "venue": "/api/venues/161", "image": "5487e79fa0ccd0b79e5d4a4c8ced005d.jpg", "contentUrl": null, "imageUrl": "5487e79fa0ccd0b79e5d4a4c8ced005d.jpg", "imageName": "5487e79fa0ccd0b79e5d4a4c8ced005d.jpg?t=1738857844"}, "saleStart": 1724148000, "saleEnd": 1740279600, "createdAt": 1738857695, "updatedAt": 1738857695, "isActive": true}, "resaleValue": 12150, "facialValue": 13500, "consumer": {"id": 45049, "hasAvatar": true, "site": "/api/site_configs/26", "publicName": "Lennard D.", "avatar": "a6835971b07994243412ed59f9c5f310.png"}, "status": 1, "currency": "EUR", "usageDateStart": 1739790000, "usageDateEnd": 1740290400, "purchaseFees": 1458, "seats": [], "notice": null, "fixedFee": 0}], "nbCartTickets": 0, "dynamicStatus": 1, "minPrice": 13608, "nbAvailableTickets": 1, "severability": false}]